demo_project_ettrainer/__init__.py
demo_project_ettrainer/modul1.py
demo_project_ettrainer/modul2.py
demo_project_ettrainer/unterpackage/__init__.py
demo_project_ettrainer/unterpackage/modul3.py
demo_project_ettrainer-0.0.1.dist-info/METADATA
demo_project_ettrainer-0.0.1.dist-info/WHEEL
demo_project_ettrainer-0.0.1.dist-info/top_level.txt
demo_project_ettrainer-0.0.1.dist-info/RECORD
